geckodriver
grants/__init__.py
grants/append_to_json.py
grants/award_upload.py
grants/awards_to_json.py
grants/csv_to_excel.py
grants/excel_to_csv.py
grants/fed_chatgpt.py
grants/fed_download.py
grants/fed_download_opps.py
grants/fed_extract_attr.py
grants/fed_filter.py
grants/fed_select.py
grants/fed_set.py
grants/fed_size.py
grants/fed_sort.py
grants/fed_to_excel.py
grants/fed_to_html.py
grants/fed_to_json.py
grants/fieldnames.py
grants/geckodriver
grants/piv_correct_column.py
grants/piv_extract_attr.py
grants/piv_to_excel.py
grants/piv_to_fed.py
grants/piv_to_json.py
grants/pivot_to_fed.py
grants/remove_chars.py
grants/selected_fed_opps.sh
grants/toml_to_csv.py
grants-0.3.0.dist-info/METADATA
grants-0.3.0.dist-info/WHEEL
grants-0.3.0.dist-info/entry_points.txt
grants-0.3.0.dist-info/RECORD
